Notification_List/__init__.py
Notification_List/main.py
Notification_List-0.0.2.dist-info/METADATA
Notification_List-0.0.2.dist-info/WHEEL
Notification_List-0.0.2.dist-info/top_level.txt
Notification_List-0.0.2.dist-info/RECORD
